[
  {
    "name": "Forest Temple",
    "chest_unopened_img": "images/chest_closed.png",
    "chest_opened_img": "images/chest_open.png",
    "access_rules": [
      "$canCompletePrologue, Shadow_Crystal",
      "$canCompletePrologue, Lantern"
    ],
    "sections": [
      {
        "name": "Diababa",
        "access_rules": ["$canCompleteForestTemple"],
        "hosted_item": "Diababa"
      }
    ],
    "map_locations": [
      {
        "map": "Main",
        "x": 570.96,
        "y": 827.5
      }
    ]
  },
  {
    "name": "Goron Mines",
    "access_rules": [
      "$canAccessMines"
    ],
    "chest_unopened_img": "images/chest_closed.png",
    "chest_opened_img": "images/chest_open.png",
    "sections": [
      {
        "name": "Fyrus",
        "access_rules": ["$canCompleteGoronMines"],
        "hosted_item": "Fyrus"
      }
    ],
    "map_locations": [
      {
        "map": "Main",
        "x": 1030.92,
        "y": 477
      }
    ]
  },
  {
    "name": "Lakebed Temple",
    "access_rules": [
      "$canAccessLakebed"
    ],
    "chest_unopened_img": "images/chest_closed.png",
    "chest_opened_img": "images/chest_open.png",
    "sections": [
      {
        "name": "Morpheel",
        "access_rules": ["$canCompleteLakebedTemple"],
        "hosted_item": "Morpheel"
      }
    ],
    "map_locations": [
      {
        "map": "Main",
        "x": 483.96,
        "y": 597
      }
    ]
  },
  {
    "name": "Arbiters Grounds",
    "parent": "Gerudo Desert",
    "access_rules": [
      "$canAccessArbiters"
    ],
    "chest_unopened_img": "images/chest_closed.png",
    "chest_opened_img": "images/chest_open.png",
    "sections": [
      {
        "name": "Stallord",
        "access_rules": ["$canCompleteArbitersGrounds"],
        "hosted_item": "Stallord"
      }
    ],
    "map_locations": [
      {
        "map": "Main",
        "x": 180.4,
        "y": 518
      }
    ]
  },
  {
    "name": "Snowpeak Ruins",
    "access_rules": [
      "$canAccessSnowpeakRuins"
    ],
    "chest_unopened_img": "images/chest_closed.png",
    "chest_opened_img": "images/chest_open.png",
    "sections": [
      {
        "name": "Blizzeta",
        "access_rules": ["$canCompleteSnowpeakRuins"],
        "hosted_item": "Blizzeta"
      }
    ],
    "map_locations": [
      {
        "map": "Main",
        "x": 255.72,
        "y": 358
      }
    ]
  },
  {
    "name": "Temple of Time",
    "access_rules": [
      "$canAccessToT"
    ],
    "chest_unopened_img": "images/chest_closed.png",
    "chest_opened_img": "images/chest_open.png",
    "sections": [
      {
        "name": "Armogohma",
        "access_rules": ["$canCompleteTempleofTime"],
        "hosted_item": "Armogohma"
      },
      {
        "name": "Poe Behind Gate",
        "access_rules": [
          "Temple_of_Time_Small_Key:1, Shadow_Crystal, Progressive_Dominion_Rod",
          "small-keysy-enabled, Shadow_Crystal, Progressive_Dominion_Rod"
        ],
        "visibility_rules": ["poes-enabled"],
        "item_count": 1,
        "chest_unopened_img": "images/soul.png",
        "chest_opened_img": "images/soul-grey.png"
      },
      {
        "name": "Poe Above Scales",
        "access_rules": [
          "Temple_of_Time_Small_Key:2, Progressive_Bow, Spinner, $canDefeatLizalfos, Clawshot, Shadow_Crystal",
          "small-keysy-enabled, Progressive_Bow, Spinner, $canDefeatLizalfos, Clawshot, Shadow_Crystal"
        ],
        "visibility_rules": ["poes-enabled"],
        "item_count": 1,
        "chest_unopened_img": "images/soul.png",
        "chest_opened_img": "images/soul-grey.png"
      }
    ],
    "map_locations": [
      {
        "map": "Main",
        "x": 525.96,
        "y": 792
      }
    ]
  },
  {
    "name": "City in The Sky",
    "access_rules": [
      "$canAccessCiTS"
    ],
    "chest_unopened_img": "images/chest_closed.png",
    "chest_opened_img": "images/chest_open.png",
    "sections": [
      {
        "name": "Argorok",
        "access_rules": ["$canCompleteCityinTheSky"],
        "hosted_item": "Argorok"
      },
      {
        "name": "Poe Above Central Fan",
        "item_count": 1,
        "visibility_rules": ["poes-enabled"],
        "access_rules": [
          "Double_Clawshot, $canDefeatBigBaba, Iron_Boots, Shadow_Crystal"
        ],
        "chest_unopened_img": "images/soul-grey.png",
        "chest_opened_img": "images/soul.png"
      }
    ],
    "map_locations": [
      {
        "map": "Main",
        "x": 456,
        "y": 632
      }
    ]
  },
  {
    "name": "Palace of Twilight",
    "chest_unopened_img": "images/chest_closed.png",
    "chest_opened_img": "images/chest_open.png",
    "access_rules": [
      "$canAccessPoT"
    ],
    "sections": [
      {
        "name": "Zant",
        "access_rules": ["$canCompletePalaceofTwilight"],
        "hosted_item": "Zant"
      },
      {
        "name": "Big Key Chest",
        "access_rules": [
          "Progressive_Sword_4, Double_Clawshot, Shadow_Crystal, Palace_of_Twilight_Small_Key:5",
          "Progressive_Sword_4, Double_Clawshot, Shadow_Crystal, small-keysy-enabled"
        ],
        "item_count": 1
      },
      {
        "name": "Central First Room Chest",
        "access_rules": [
          "Progressive_Sword_4, Clawshot, Shadow_Crystal, Palace_of_Twilight_Small_Key:4",
          "Progressive_Sword_4, Clawshot, Shadow_Crystal, small-keysy-enabled"
        ],
        "item_count": 1
      },
      {
        "name": "Central Outdoor Chest",
        "access_rules": [
          "Progressive_Sword_4, Clawshot, Shadow_Crystal, Palace_of_Twilight_Small_Key:5",
          "Progressive_Sword_4, Clawshot, Shadow_Crystal, small-keysy-enabled"
        ],
        "item_count": 1
      },
      {
        "name": "Central Tower Chest",
        "access_rules": [
          "Progressive_Sword_4, Clawshot, Shadow_Crystal, Palace_of_Twilight_Small_Key:6",
          "Progressive_Sword_4, Clawshot, Shadow_Crystal, small-keysy-enabled"
        ],
        "item_count": 1
      },
      {
        "name": "Collect Both Sols",
        "access_rules": [
          "$canDefeatPhantomZant, Clawshot, Shadow_Crystal, Palace_of_Twilight_Small_Key:4",
          "$canDefeatPhantomZant, Clawshot, Shadow_Crystal, small-keysy-enabled"
        ],
        "item_count": 1
      },
      {
        "name": "East Wing First Room East Alcove",
        "access_rules": [
          "$canDefeatPhantomZant, Clawshot, Shadow_Crystal, Palace_of_Twilight_Small_Key:2, Progressive_Sword_4",
          "$canDefeatPhantomZant, Clawshot, Shadow_Crystal, Palace_of_Twilight_Small_Key:4",
          "$canDefeatPhantomZant, Clawshot, Shadow_Crystal, small-keysy-enabled, Progressive_Sword_4",
          "$canDefeatPhantomZant, Clawshot, Shadow_Crystal, small-keysy-enabled"
        ],
        "item_count": 1
      },
      {
        "name": "East Wing First Room North Small Chest",
        "access_rules": [
          "$canDefeatPhantomZant, Clawshot, Shadow_Crystal, Palace_of_Twilight_Small_Key:2",
          "$canDefeatPhantomZant, Clawshot, Shadow_Crystal, small-keysy-enabled"
        ],
        "item_count": 1
      },
      {
        "name": "East Wing First Room West Alcove",
        "access_rules": [
          "$canDefeatPhantomZant, Clawshot, Shadow_Crystal, Palace_of_Twilight_Small_Key:2, Progressive_Sword_4",
          "$canDefeatPhantomZant, Clawshot, Shadow_Crystal, Palace_of_Twilight_Small_Key:4",
          "$canDefeatPhantomZant, Clawshot, Shadow_Crystal, small-keysy-enabled, Progressive_Sword_4",
          "$canDefeatPhantomZant, Clawshot, Shadow_Crystal, small-keysy-enabled"
        ],
        "item_count": 1
      },
      {
        "name": "East Wing First Room Zant Head Chest",
        "access_rules": [
          "$canDefeatPhantomZant, Clawshot, Shadow_Crystal, Palace_of_Twilight_Small_Key:2",
          "$canDefeatPhantomZant, Clawshot, Shadow_Crystal, small-keysy-enabled"
        ],
        "item_count": 1
      },
      {
        "name": "East Wing Second Room Northeast Chest",
        "access_rules": [
          "$canDefeatPhantomZant, Double_Clawshot, Shadow_Crystal, Palace_of_Twilight_Small_Key:3",
          "$canDefeatPhantomZant, Double_Clawshot, Shadow_Crystal, small-keysy-enabled"
        ],
        "item_count": 1
      },
      {
        "name": "East Wing Second Room Northwest Chest",
        "access_rules": [
          "$canDefeatPhantomZant, Clawshot, Shadow_Crystal, Palace_of_Twilight_Small_Key:3",
          "$canDefeatPhantomZant, Clawshot, Shadow_Crystal, small-keysy-enabled"
        ],
        "item_count": 1
      },
      {
        "name": "East Wing Second Room Southeast Chest",
        "access_rules": [
          "$canDefeatPhantomZant, Double_Clawshot, Shadow_Crystal, Palace_of_Twilight_Small_Key:3",
          "$canDefeatPhantomZant, Double_Clawshot, Shadow_Crystal, small-keysy-enabled"
        ],
        "item_count": 1
      },
      {
        "name": "East Wing Second Room Southwest Chest",
        "access_rules": [
          "$canDefeatPhantomZant, Double_Clawshot, Shadow_Crystal, Palace_of_Twilight_Small_Key:3",
          "$canDefeatPhantomZant, Double_Clawshot, Shadow_Crystal, small-keysy-enabled"
        ],
        "item_count": 1
      },
      {
        "name": "West Wing Chest Behind Wall of Darkness",
        "access_rules": [
          "Progressive_Sword_4, Clawshot"
        ],
        "item_count": 1
      },
      {
        "name": "West Wing First Room Central Chest",
        "access_rules": [
          "$canDefeatZantHead"
        ],
        "item_count": 1
      },
      {
        "name": "West Wing Second Room Central Chest",
        "access_rules": [
          "$canDefeatPhantomZant, Clawshot, Palace_of_Twilight_Small_Key:1",
          "$canDefeatPhantomZant, Clawshot, small-keysy-enabled"
        ],
        "item_count": 1
      },
      {
        "name": "West Wing Second Room Lower South Chest",
        "access_rules": [
          "$canDefeatPhantomZant, Clawshot, Palace_of_Twilight_Small_Key:1",
          "$canDefeatPhantomZant, Clawshot, small-keysy-enabled"
        ],
        "item_count": 1
      },
      {
        "name": "West Wing Second Room Southeast Chest",
        "access_rules": [
          "$canDefeatPhantomZant, Double_Clawshot, Palace_of_Twilight_Small_Key:1",
          "$canDefeatPhantomZant, Double_Clawshot, small-keysy-enabled"
        ],
        "item_count": 1
      },
      {
        "name": "Zant Heart Container",
        "access_rules": [
          "Progressive_Sword_4, Shadow_Crystal, Palace_of_Twilight_Small_Key:7, Palace_of_Twilight_Big_Key, $canDefeatZant",
          "Progressive_Sword_4, Shadow_Crystal, Palace_of_Twilight_Small_Key:7, boss-keysy-enabled, $canDefeatZant",
          "Progressive_Sword_4, Shadow_Crystal, small-keysy-enabled, Palace_of_Twilight_Big_Key, $canDefeatZant",
          "Progressive_Sword_4, Shadow_Crystal, small-keysy-enabled, boss-keysy-enabled, $canDefeatZant"
        ],
        "chest_unopened_img": "images/HC.png",
        "chest_opened_img": "images/HC_grey.png",
        "item_count": 1
      }
    ],
    "map_locations": [
      {
        "map": "Main",
        "x": 180,
        "y": 468
      }
    ]
  },
  {
    "name": "Hyrule Castle",
    "chest_unopened_img": "images/chest_closed.png",
    "chest_opened_img": "images/chest_open.png",
    "access_rules": [
      "$canAccessLanayru, $canCompleteMDH, castle-vanilla, $canCompletePalaceofTwilight",
      "$canAccessLanayru, $canCompleteMDH, castle-fused, Progressive_Fused_Shadow_3",
      "$canAccessLanayru, $canCompleteMDH, castle-mirror, Progressive_Mirror_Shard_3",
      "$canAccessLanayru, $canCompleteMDH, castle-all,Diababa,Fyrus,Morpheel,Stallord,Blizzeta,Armogohma,Argorok,Zant",
      "$canAccessLanayru, $canCompleteMDH, castle-open"
    ],
    "sections": [
      {
        "name": "Ganondorf",
        "access_rules": [
          "$canDefeatFinalBoss"
        ],
        "hosted_item": "Ganondorf"
      }
    ],
    "map_locations": [
      {
        "map": "Main",
        "x": 645.36,
        "y": 457
      }
    ]
  }
]